Metadata-Version: 1.0
Name: distributions-tm1611
Version: 0.1
Summary: distributions package
Home-page: UNKNOWN
Author: Timo Meiendresch
Author-email: tmeiendresch@gmx.de
License: UNKNOWN
Platform: UNKNOWN
